{"nodes": [{"id": "c_users_yash_desktop_hackathon_techfluence_skillgraph_src_recruiter_ui_components_herograph_tsx", "label": "HeroGraph.tsx", "file_type": "code", "source_file": "C:\\Users\\Yash\\Desktop\\hackathon\\TechFluence\\SkillGraph\\src\\recruiter-ui\\components\\HeroGraph.tsx", "source_location": "L1"}, {"id": "herograph_herograph", "label": "HeroGraph()", "file_type": "code", "source_file": "C:\\Users\\Yash\\Desktop\\hackathon\\TechFluence\\SkillGraph\\src\\recruiter-ui\\components\\HeroGraph.tsx", "source_location": "L19"}], "edges": [{"source": "c_users_yash_desktop_hackathon_techfluence_skillgraph_src_recruiter_ui_components_herograph_tsx", "target": "react", "relation": "imports_from", "confidence": "EXTRACTED", "source_file": "C:\\Users\\Yash\\Desktop\\hackathon\\TechFluence\\SkillGraph\\src\\recruiter-ui\\components\\HeroGraph.tsx", "source_location": "L1", "weight": 1.0}, {"source": "c_users_yash_desktop_hackathon_techfluence_skillgraph_src_recruiter_ui_components_herograph_tsx", "target": "herograph_herograph", "relation": "contains", "confidence": "EXTRACTED", "source_file": "C:\\Users\\Yash\\Desktop\\hackathon\\TechFluence\\SkillGraph\\src\\recruiter-ui\\components\\HeroGraph.tsx", "source_location": "L19", "weight": 1.0}], "raw_calls": [{"caller_nid": "herograph_herograph", "callee": "useRef", "source_file": "C:\\Users\\Yash\\Desktop\\hackathon\\TechFluence\\SkillGraph\\src\\recruiter-ui\\components\\HeroGraph.tsx", "source_location": "L20"}, {"caller_nid": "herograph_herograph", "callee": "useRef", "source_file": "C:\\Users\\Yash\\Desktop\\hackathon\\TechFluence\\SkillGraph\\src\\recruiter-ui\\components\\HeroGraph.tsx", "source_location": "L21"}, {"caller_nid": "herograph_herograph", "callee": "useEffect", "source_file": "C:\\Users\\Yash\\Desktop\\hackathon\\TechFluence\\SkillGraph\\src\\recruiter-ui\\components\\HeroGraph.tsx", "source_location": "L23"}]}